irisify/__init__.py
irisify/__meta__.py
irisify/api.py
irisify/async_api.py
irisify/exceptions.py
irisify/models.py
irisify-0.1.2.dist-info/METADATA
irisify-0.1.2.dist-info/WHEEL
irisify-0.1.2.dist-info/licenses/LICENSE
irisify-0.1.2.dist-info/RECORD
